{
  "resource": "Dog Walking",
  "resource_explanation": null,
  "http_method": "GET",
  "route": "dog-walkings/:id",
  "description": "GET - Dog walking by id",
  "explanation": null,
  "parameters": [

  ],
  "response_fields": [

  ],
  "requests": [
    {
      "request_method": "GET",
      "request_path": "dog-walkings/1",
      "request_body": null,
      "request_headers": {
        "Authorization": "Bearer eyJhbGciOiJIUzI1NiJ9.eyJuYW1lIjoiQ2FtaWxhIiwicm9sZSI6InBldF9vd25lciIsInN1YiI6IjMiLCJzY3AiOiJ1c2VyIiwiYXVkIjpudWxsLCJpYXQiOjE1NzM0NDI1NjAsImV4cCI6MTU3NDA0NzM2MCwianRpIjoiZGNlNmM3NjktNzA2Yy00ZjUyLTk2MmQtMmY2NzA1NjE3ZjgwIn0.NNhpOJo6iqKa6EmLc-6HIKrVPA8Ze6P6uyxv2de0Clc",
        "Accept": "application/json",
        "Content-Type": "application/json",
        "Host": "example.org",
        "Cookie": ""
      },
      "request_query_parameters": {
      },
      "request_content_type": "application/json",
      "response_status": 200,
      "response_status_text": "OK",
      "response_body": "{\n  \"id\": 1,\n  \"duration\": 30,\n  \"latitude\": \"-23.534296\",\n  \"longitude\": \"-46.724113\",\n  \"begin_date\": \"2019-11-09T16:32:00.000Z\",\n  \"end_date\": \"2019-11-09T17:01:00.000Z\",\n  \"scheduled_date\": \"2019-11-09T16:30:00.000Z\",\n  \"price\": 40.0,\n  \"created_at\": \"2019-11-11T03:22:39.890Z\",\n  \"updated_at\": \"2019-11-11T03:22:39.890Z\",\n  \"user_id\": 1,\n  \"dog_walking_status_id\": 4,\n  \"walk_duration\": \"00:29:00\",\n  \"dogs\": [\n    {\n      \"id\": 1,\n      \"name\": \"Lola\",\n      \"age\": 2,\n      \"created_at\": \"2019-11-11T03:22:39.583Z\",\n      \"updated_at\": \"2019-11-11T03:22:39.583Z\",\n      \"user_id\": 3\n    },\n    {\n      \"id\": 2,\n      \"name\": \"Duda\",\n      \"age\": 13,\n      \"created_at\": \"2019-11-11T03:22:39.600Z\",\n      \"updated_at\": \"2019-11-11T03:22:39.600Z\",\n      \"user_id\": 3\n    }\n  ],\n  \"dog_walking_status\": {\n    \"id\": 4,\n    \"name\": \"done\",\n    \"created_at\": \"2019-11-11T03:22:39.687Z\",\n    \"updated_at\": \"2019-11-11T03:22:39.687Z\"\n  },\n  \"user\": {\n    \"id\": 1,\n    \"name\": \"João\",\n    \"email\": \"joao@gmail.com\",\n    \"created_at\": \"2019-11-11T03:22:39.424Z\",\n    \"updated_at\": \"2019-11-11T03:22:39.424Z\",\n    \"role_id\": 2,\n    \"image\": \"https://images.pexels.com/photos/220453/pexels-photo-220453.jpeg?auto=compress&cs=tinysrgb&h=400&w=400\"\n  }\n}",
      "response_headers": {
        "Content-Type": "application/json; charset=utf-8",
        "ETag": "W/\"1bf8f8d75b3b788f32302c1489e46db4\"",
        "Cache-Control": "max-age=0, private, must-revalidate",
        "X-Request-Id": "85263dfa-01c5-40ee-a65e-557137210482",
        "X-Runtime": "0.032733",
        "Vary": "Origin",
        "Content-Length": "1007"
      },
      "response_content_type": "application/json; charset=utf-8",
      "curl": null
    }
  ]
}